pravegaBhu-0.3.8.dist-info/METADATA
pravegaBhu-0.3.8.dist-info/WHEEL
pravega_client/__init__.py
pravega_client/pravega_client.cp310-win_amd64.pyd
pravegaBhu-0.3.8.dist-info/RECORD
