Metadata-Version: 2.1
Name: pravegaBhu
Version: 0.3.8
Summary: Pravega client
Keywords: streaming,client,pravega
Author: Pravega Community
License: Apache-2.0
Project-URL: Source Code, https://github.com/pravega/pravega-client-python
